pbp_batch/__init__.py
pbp_batch/_deploy.py
pbp_batch/cli.py
pbp_batch/cli_bkp.py
pbp_batch/core.py
pbp_batch/prefect_script.py
pbp_batch-0.0.1.dist-info/licenses/LICENSE
pbp_batch-0.0.1.dist-info/METADATA
pbp_batch-0.0.1.dist-info/WHEEL
pbp_batch-0.0.1.dist-info/entry_points.txt
pbp_batch-0.0.1.dist-info/top_level.txt
pbp_batch-0.0.1.dist-info/RECORD
